{
  "doc": "vlm-v1m1v1-dyn-b-source-closure-2026-07-23",
  "verdict": "CLEAN_BASE_SOURCE_CLOSURE_PASS",
  "next_gate": "ONE_DYN_B_PREFLIGHT_MAY_BE_REQUESTED",
  "formal_dyn_b_capture_run": false,
  "build_count": 1,
  "smoke_count": 1,
  "retry_count": 0,
  "base_image": {
    "tag": "gmdisturb:b4-p010-20260721",
    "id": "sha256:defe95e7df25b73cb08c3bb768c3e18d15807d0ae38fc52135d5474d3c820b68"
  },
  "image": {
    "tag": "gmdisturb:e01-dyn-b-clean-m1v1-20260723",
    "id": "sha256:19112b9c1e8f63c04e8ef777840da823f0323b55f950f432f27ea8ba9d4cf14f",
    "created": "2026-07-23T14:38:11.953179399+08:00",
    "dockerfile": "g1_ur10e_disturbance/docker/Dockerfile.e01-dyn-b-clean-m1v1",
    "build_exit": 0,
    "build_elapsed_seconds": 1
  },
  "closure": {
    "entry_file": "g1_ur10e_disturbance/scripts/run_phase3.py",
    "closure_count": 31,
    "unresolved_local_imports": 0,
    "scene_camera_override_present": true,
    "missing_in_image": 0,
    "members": [
      "config_loader.py",
      "dual_env_cfg.py",
      "dynamic_audit_csv.py",
      "dynamic_sweep_proxy.py",
      "event_csv.py",
      "g1_arm_controller.py",
      "g1_disturbance_controller.py",
      "g1_virtual_hand.py",
      "g1_vlm_client.py",
      "g1_walk_controller.py",
      "mat_event_detector.py",
      "mdp/__init__.py",
      "mdp/gm_safety_obs.py",
      "mdp/tactile_obs.py",
      "mdp/terminations.py",
      "mdp/walk_action.py",
      "paths.py",
      "per_part_state.py",
      "protocol_vhand.py",
      "safety_adapter.py",
      "scenarios.py",
      "scene_camera_override.py",
      "scripts/numpy_abi_guard.py",
      "scripts/pick_and_place_policy.py",
      "scripts/run_phase3.py",
      "seed_utils.py",
      "spawn_utils.py",
      "test_metrics.py",
      "ur10e_controller.py",
      "vendored/robot_cfg.py",
      "vendored/ur10e_cfg.py"
    ]
  },
  "smoke": {
    "runner": "docker/run.sh + capture_one_shot_runner.py",
    "scenario": "outer_lateral_patrol",
    "seed": 43,
    "max_steps": 1,
    "exit_code": 0,
    "returncode_raw": 0,
    "elapsed_monotonic_sec": 30.87987304,
    "csv_path": "g1_ur10e_disturbance/results/paper_demo/v1m1v1_dyn_b_clean_runtime_20260723/safety_logs/phase3.csv",
    "csv_exists": true,
    "csv_rows": 2,
    "numpy_pre_ok": true,
    "numpy_post_ok": true,
    "numpy_root_pre": "/isaac-sim/extscache/omni.kit.pip_archive-0.0.0+69cbf6ad.lx64.cp311/pip_prebundle",
    "numpy_root_post": "/isaac-sim/extscache/omni.kit.pip_archive-0.0.0+69cbf6ad.lx64.cp311/pip_prebundle",
    "numpy_single_root": true,
    "typing_extensions_pre_paramspec": true,
    "typing_extensions_post_paramspec": true,
    "typing_extensions_file": "/isaac-sim/kit/python/lib/python3.11/site-packages/typing_extensions.py",
    "forbidden_hits": 0,
    "post_count_stdout_stderr": 0,
    "xid_count_stdout_stderr": 0,
    "traceback": false,
    "missing_module": false,
    "abi_error": false,
    "paramspec_error": false,
    "device_lost": false
  },
  "runtime_origins": {
    "numpy_pre_json": "g1_ur10e_disturbance/results/paper_demo/v1m1v1_dyn_b_clean_runtime_20260723/meta/numpy_origin_pre.json",
    "numpy_post_json": "g1_ur10e_disturbance/results/paper_demo/v1m1v1_dyn_b_clean_runtime_20260723/meta/numpy_origin_post.json",
    "typing_extensions_pre_json": "g1_ur10e_disturbance/results/paper_demo/v1m1v1_dyn_b_clean_runtime_20260723/meta/typing_extensions_pre.json",
    "typing_extensions_post_json": "g1_ur10e_disturbance/results/paper_demo/v1m1v1_dyn_b_clean_runtime_20260723/meta/typing_extensions_post.json"
  },
  "residue": {
    "leftover_container_for_image": false
  },
  "constraints": {
    "package_mutation": false,
    "no_pip_conda_apt": true,
    "no_numpy_typing_extensions_package_change": true,
    "no_vlm_perception_sam2_post_change": true,
    "no_safety_usd_b0_b4_change": true
  },
  "results_dir": "g1_ur10e_disturbance/results/paper_demo/v1m1v1_dyn_b_clean_runtime_20260723"
}
